mai_cloggingmcp/__init__.py
mai_cloggingmcp-0.1.0.dist-info/METADATA
mai_cloggingmcp-0.1.0.dist-info/WHEEL
mai_cloggingmcp-0.1.0.dist-info/entry_points.txt
mai_cloggingmcp-0.1.0.dist-info/RECORD
