Metadata-Version: 2.4
Name: mai-cloggingmcp
Version: 0.1.0
Summary: Add your description here
Author-email: Dan Xu <dan.xu@microsoft.com>
Requires-Python: >=3.13
Requires-Dist: mcp[cli]>=1.11.0
